README.md
setup.py
mofang23/aplot.py
mofang23/datamash.py
mofang23/geno.py
mofang23/merge.py
mofang23.egg-info/PKG-INFO
mofang23.egg-info/SOURCES.txt
mofang23.egg-info/dependency_links.txt
mofang23.egg-info/requires.txt
mofang23.egg-info/top_level.txt