Metadata-Version: 1.2
Name: mofang23
Version: 0.0.1.4
Summary: Tool of Asdil
Home-page: https://github.com/Asdil/mofang23
Author: Asdil
Author-email: jpl4job@126.com
Maintainer: Asdil
Maintainer-email: jpl4job@126.com
License: MIT
Platform: all
Classifier: Environment :: Web Environment
Classifier: Intended Audience :: Developers
Classifier: Operating System :: OS Independent
Classifier: Topic :: Text Processing :: Indexing
Classifier: Topic :: Utilities
Classifier: Topic :: Internet
Classifier: Topic :: Software Development :: Libraries :: Python Modules
Classifier: Programming Language :: Python
Classifier: Programming Language :: Python :: 3
Classifier: Programming Language :: Python :: 3.5
Classifier: Programming Language :: Python :: 3.6
Classifier: Programming Language :: Python :: 3.7
